nadap/__init__.py
nadap/base.py
nadap/doc.py
nadap/errors.py
nadap/nadap.py
nadap/references.py
nadap/results.py
nadap/schema.py
nadap/mixin/accuracy.py
nadap/mixin/allow_duplicate.py
nadap/mixin/allowed_value.py
nadap/mixin/ip.py
nadap/mixin/min_max.py
nadap/mixin/not_allowed_value.py
nadap/mixin/ranges.py
nadap/mixin/regex_mode.py
nadap/mixin/replace_empty_to.py
nadap/types/any.py
nadap/types/base.py
nadap/types/bgp_as.py
nadap/types/bgp_community.py
nadap/types/bool.py
nadap/types/bool_false.py
nadap/types/bool_true.py
nadap/types/byte4_value.py
nadap/types/dict.py
nadap/types/enum.py
nadap/types/float.py
nadap/types/hostname.py
nadap/types/hostname_or_ip.py
nadap/types/idlist.py
nadap/types/int.py
nadap/types/int16.py
nadap/types/int32.py
nadap/types/int8.py
nadap/types/ip4_address.py
nadap/types/ip4_interface.py
nadap/types/ip4_network.py
nadap/types/ip6_address.py
nadap/types/ip6_interface.py
nadap/types/ip6_network.py
nadap/types/ip_address.py
nadap/types/ip_interface.py
nadap/types/ip_network.py
nadap/types/list.py
nadap/types/mac_address.py
nadap/types/multitype.py
nadap/types/multitype2.py
nadap/types/none.py
nadap/types/number.py
nadap/types/str.py
nadap/types/str_float.py
nadap/types/str_int.py
nadap/types/str_number.py
nadap/types/uint16.py
nadap/types/uint32.py
nadap/types/uint8.py
nadap-2.1.0.dist-info/METADATA
nadap-2.1.0.dist-info/WHEEL
nadap-2.1.0.dist-info/licenses/LICENSE
nadap-2.1.0.dist-info/RECORD
