Metadata-Version: 2.4
Name: nadap
Version: 2.1.0
Summary: nadap validates and pre-process data structure, data types and values
Project-URL: Documentation, https://nadap.readthedocs.io/en/latest/
Project-URL: Home, https://gitlab.com/ko.no/nadap
Project-URL: Tracker, https://gitlab.com/ko.no/nadap/-/issues
Author-email: Korte Noack <korte@8lacht.de>
License-File: LICENSE
Classifier: Development Status :: 5 - Production/Stable
Classifier: Intended Audience :: Developers
Classifier: License :: OSI Approved :: GNU General Public License v3 (GPLv3)
Classifier: Operating System :: OS Independent
Classifier: Programming Language :: Python :: 3.12
Classifier: Programming Language :: Python :: 3.13
Classifier: Programming Language :: Python :: 3.14
Requires-Python: >=3.10
